easy_workdays/__init__.py
easy_workdays/workdays.py
easy_workdays-0.1.0.dist-info/METADATA
easy_workdays-0.1.0.dist-info/WHEEL
easy_workdays-0.1.0.dist-info/RECORD
